[
    {
      "id": "0",
      "env": "prod",
      "ComputerName": "DLNWS02",
      "Service": "Apache2.2.31_ApacheXML",
      "priority": "2",
      "predecessor": "0"
    },
    {
      "id": "1",
      "env": "prod",
      "ComputerName": "DLNWS02",
      "Service": "TMW TruckMate API Service",
      "priority": "2",
      "predecessor": "0"
    },
    {
      "id": "2",
      "env": "prod",
      "ComputerName": "dlptmcom00",
      "Service": "MileServ1",
      "priority": "1",
      "predecessor": "0"
    },
    {
      "id": "3",
      "env": "prod",
      "ComputerName": "dlptmcom00",
      "Service": "MadHostSvc7",
      "priority": "2",
      "predecessor": "0"
    },
    {
      "id": "4",
      "env": "prod",
      "ComputerName": "DLPSYNPRC01",
      "Service": "SynergizeProcessServer",
      "priority": "2",
      "predecessor": "0"
    },
    {
      "id": "5",
      "env": "prod",
      "ComputerName": "DLPTMDWG02",
      "Service": "MadHostSvc2",
      "priority": "2",
      "predecessor": "0"
    },
    {
      "id": "6",
      "env": "prod",
      "ComputerName": "DLPTMDWG02",
      "Service": "MadHostSvc",
      "priority": "2",
      "predecessor": "0"
    },
    {
      "id": "7",
      "env": "prod",
      "ComputerName": "DLPTMEDI00",
      "Service": "MadHostSvc3",
      "priority": "2",
      "predecessor": "0"
    },
    {
      "id": "8",
      "env": "prod",
      "ComputerName": "DLPTMEDI00",
      "Service": "MadHostSvc2",
      "priority": "2",
      "predecessor": "0"
    },
    {
      "id": "9",
      "env": "prod",
      "ComputerName": "DLPTMDWG00",
      "Service": "Schedule",
      "priority": "2",
      "predecessor": "0"
    },
    {
      "id": "10",
      "env": "prod",
      "ComputerName": "DLPTMMOB00",
      "Service": "MobCommService",
      "priority": "2",
      "predecessor": "0"
    },
    {
      "id": "11",
      "env": "prod",
      "ComputerName": "DLPTMART00",
      "Service": "SERVICE_NAME",
      "priority": "2",
      "predecessor": "0"
    },
    {
      "id": "12",
      "env": "rep",
      "ComputerName": "DLNWS02",
      "Service": "Apache2.2.31_ApacheXML",
      "priority": "2",
      "predecessor": "0"
    },
    {
      "id": "13",
      "env": "test",
      "ComputerName": "DLNWS02",
      "Service": "Apache2.2.31_ApacheXML",
      "priority": "2",
      "predecessor": "0"
    },
    {
      "id": "14",
      "env": "dev",
      "ComputerName": "DLNWS02",
      "Service": "Apache2.2.31_ApacheXML",
      "priority": "2",
      "predecessor": "0"
    },
    {
      "id": "15",
      "env": "project",
      "ComputerName": "DLDTMWEB00 ",
      "Service": "Apache2.2.31_DEV",
      "priority": "2",
      "predecessor": "0"
    },
    {
      "id": "16",
      "env": "prod",
      "ComputerName": "DLNWS02",
      "Service": "Schedule",
      "priority": "2",
      "predecessor": "0"
    },
    {
      "id": "17",
      "env": "prod",
      "ComputerName": "dlptmcom00",
      "Service": "Schedule",
      "priority": "2",
      "predecessor": "0"
    },
    {
      "id": "18",
      "env": "prod",
      "ComputerName": "DLPSUNPRC01",
      "Service": "Schedule",
      "priority": "2",
      "predecessor": "0"
    },
    {
      "id": "19",
      "env": "prod",
      "ComputerName": "DLPTMDWG02",
      "Service": "Schedule",
      "priority": "2",
      "predecessor": "0"
    },
    {
      "id": "20",
      "env": "prod",
      "ComputerName": "DLPTMEDI00",
      "Service": "Schedule",
      "priority": "2",
      "predecessor": "0"
    },
    {
      "id": "21",
      "env": "prod",
      "ComputerName": "DLPTMMOB00",
      "Service": "Schedule",
      "priority": "2",
      "predecessor": "0"
    },
    {
      "id": "22",
      "env": "project",
      "ComputerName": "DLDYLTDEVWM",
      "Service": "Tomcat8",
      "priority": "2",
      "predecessor": "0"
    },
    {
      "id": "23",
      "env": "rep",
      "ComputerName": "DLPTMDB07",
      "Service": "sqdr+derby",
      "priority": "2",
      "predecessor": "0"
    },
    {
      "id": "24",
      "env": "project",
      "ComputerName": "DLPTMDB07",
      "Service": "sqdr+jetty",
      "priority": "2",
      "predecessor": "0"
    },
    {
    "id": "25",
    "env": "project",
    "ComputerName": "DLPTMDB07",
    "Service": "sqdr+capagent",
    "priority": "2",
    "predecessor": "0"
    },
    {
      "id": "26",
      "env": "project",
      "ComputerName": "DLPTMDB07",
      "Service": "SQDRSVC",
      "priority": "2",
      "predecessor": "0"
    }
]
